{
    "Parameters": [
        {
            "ParameterKey": "SystemName",
            "ParameterValue": "TestDocker"
        },
        {
            "ParameterKey": "EnvType",
            "ParameterValue": "prod"
        },
        {
            "ParameterKey": "isFifoTopic",
            "ParameterValue": "false"
        },
        {
            "ParameterKey": "SubscriptionProtocol",
            "ParameterValue": "email"
        },
        {
            "ParameterKey": "EndpointAddress",
            "ParameterValue": "prod用メールアドレス"
        }
    ]
}